.coveragerc
.gitignore
AUTHORS.rst
CONTRIBUTING.rst
LICENSE
MANIFEST.in
Makefile
Pipfile
Pipfile.lock
README.rst
setup.cfg
setup.py
tox.ini
.circleci/config.yml
docs/Makefile
docs/api.rst
docs/authors.rst
docs/conf.py
docs/contributing.rst
docs/eeee.rst
docs/index.rst
docs/_build/html/_images/inheritance-ada7ed68ee09e1e3d793ccc8021b07e65b885967.png
docs/_build/html/_static/ajax-loader.gif
docs/_build/html/_static/comment-bright.png
docs/_build/html/_static/comment-close.png
docs/_build/html/_static/comment.png
docs/_build/html/_static/down-pressed.png
docs/_build/html/_static/down.png
docs/_build/html/_static/file.png
docs/_build/html/_static/minus.png
docs/_build/html/_static/plus.png
docs/_build/html/_static/up-pressed.png
docs/_build/html/_static/up.png
docs/_templates/layout.html
eeee/__init__.py
eeee/event.py
eeee/exceptions.py
eeee.egg-info/PKG-INFO
eeee.egg-info/SOURCES.txt
eeee.egg-info/dependency_links.txt
eeee.egg-info/not-zip-safe
eeee.egg-info/requires.txt
eeee.egg-info/top_level.txt
tests/__init__.py
tests/test_event.py
tests/test_pub_sub.py
tests/test_publisher.py
tests/test_subscriber.py
tests/test_utils.py