Metadata-Version: 1.1
Name: eeee
Version: 0.1.1
Summary: Extremely Ease Event Emitter. Pub-Sub implementation.
Home-page: https://github.com/pawelzny/eeee
Author: Paweł Zadrożny
Author-email: pawel.zny@gmail.com
License: ISC
Keywords: eeee,event,emitter,signals
Platform: UNKNOWN
Classifier: Development Status :: 3 - Alpha
Classifier: Intended Audience :: Developers
Classifier: Natural Language :: English
Classifier: Topic :: Software Development
Classifier: Topic :: Software Development :: Libraries :: Python Modules
Classifier: Programming Language :: Python :: 3.5
Classifier: Programming Language :: Python :: 3.6
Classifier: Programming Language :: Python :: 3 :: Only
Classifier: Programming Language :: Python :: Implementation :: CPython
Classifier: Programming Language :: Python :: Implementation :: PyPy
Classifier: Framework :: AsyncIO
Classifier: License :: OSI Approved :: ISC License (ISCL)
